ChartSmith/__init__.py
ChartSmith/chartsmith.py
tests/__init__.py
tests/test_chartsmith.py
ChartSmith-0.1.2.dist-info/LICENSE.txt
ChartSmith-0.1.2.dist-info/METADATA
ChartSmith-0.1.2.dist-info/WHEEL
ChartSmith-0.1.2.dist-info/top_level.txt
ChartSmith-0.1.2.dist-info/RECORD
