Metadata-Version: 2.1
Name: ChartSmith
Version: 0.1.2
Summary: A package for creating well-formatted, well-labeled visualizations
Home-page: https://github.com/tullyoleary/ChartSmith
Author: Tully OLeary
Author-email: tullyro@gmail.com
Classifier: Programming Language :: Python :: 3
Classifier: License :: OSI Approved :: MIT License
Classifier: Operating System :: OS Independent
Requires-Python: >=3.6
License-File: LICENSE.txt
Requires-Dist: matplotlib>=3.0.0
Requires-Dist: seaborn>=0.11.0
